{
  "$schema": "https://mintlify.com/docs.json",
  "theme": "mint",
  "name": "inkrealm nexus",
  "openapi": "/api/v1/openapi.json",
  "metadata": {
    "description": "inkrealm — music, art, creativity, and projects by the writer and artist",
    "keywords": "creative, writing, visual arts, music, poetry, film, band, tiktok, ai, nexus"
  },
  "colors": {
    "primary": "#ff0000",
    "light": "#ff3333",
    "dark": "#cc0000"
  },
  "favicon": "/favicon.svg",
  "navigation": {
    "tabs": [
      {
        "tab": "Realms",
        "groups": [
          {
            "group": "Core Realms",
            "pages": [
              "index",
              "1991",
              "runway",
              "minraud"
            ]
          },
          {
            "group": "Creative Nexus",
            "pages": [
              "deluxe",
              "nous",
              "trix",
              "atari"
            ]
          },
          {
            "group": "WordStar Projects",
            "pages": [
              "dreamweaver",
              "displaywriter",
              "dejavuglitches",
              "wip"
            ]
          }
        ]
      },
      {
        "tab": "Digital Archive",
        "groups": [
          {
            "group": "Downloads",
            "pages": [
              "apk"
            ]
          },
          {
            "group": "Extras",
            "pages": [
              "twoskinnygirls",
              "2741",
              "svg",
              "apartment7a"
            ]
          },
          {
            "group": "Revolutions",
            "pages": [
              "synthword",
              "poesia",
              "tvc15",
              "ie"
            ]
          }
        ]
      },
      {
        "tab": "API Reference",
        "groups": [
          {
            "group": "inkrealm Creative API",
            "pages": [
              "api-reference/introduction"
            ]
          }
        ]
      }
    ]
  },
  "logo": {
    "light": "/logo/light.svg",
    "dark": "/logo/dark.svg",
    "href": "https://inkrealm.info"
  },
  "navbar": {
    "links": [
      {
        "label": "Contact",
        "href": "tel:+16468019713"
      },
      {
        "label": "Status",
        "href": "https://wordstar.ilert.io/"
      },
      {
        "label": "Sitemap",
        "href": "https://inkrealm.info/sitemap"
      }
    ],
    "primary": {
      "type": "button",
      "label": "Enter Nexus",
      "href": "https://inkrealm.info"
    }
  },
  "contextual": {
    "options": [
      "copy",
      "view"
    ]
  },
  "footer": {
    "socials": {
      "x": "https://x.com/inkrealm",
      "github": "https://github.com/ghostm68",
      "linkedin": "https://linkedin.com/company/inkrealm",
      "instagram": "https://instagram.com/inkrealm"
    }
  },
  "topbarCtaButton": {
    "type": "github",
    "url": "https://github.com/ghostm68/inktwo"
  },
  "modeToggle": {
    "default": "dark",
    "isHidden": false
  },
  "backgroundImage": "/backgrounds/ink-bg.jpg"
}